{"config": {"view": {"continuousWidth": 300, "continuousHeight": 300}}, "data": {"name": "data-11530baf9c0bb029a82eb8806a4177d9"}, "mark": {"type": "line"}, "encoding": {"tooltip": [{"field": "date", "format": "%Y", "title": "Year", "type": "temporal"}, {"field": "gdp_per_capita", "title": "Value", "type": "quantitative"}], "x": {"axis": {"format": "%Y", "grid": true, "tickCount": "year", "title": null}, "field": "date", "type": "temporal"}, "y": {"axis": {"title": "USD"}, "field": "gdp_per_capita", "type": "quantitative"}}, "height": 100, "title": "GDP Per Capita (Current USD)", "width": 200, "$schema": "https://vega.github.io/schema/vega-lite/v5.20.1.json", "datasets": {"data-11530baf9c0bb029a82eb8806a4177d9": [{"economy": "IDN", "date": "1990-01-01T00:00:00", "gdp_per_capita": 578.420121135382}, {"economy": "IDN", "date": "1991-01-01T00:00:00", "gdp_per_capita": 624.387495384411}, {"economy": "IDN", "date": "1992-01-01T00:00:00", "gdp_per_capita": 673.67103954742}, {"economy": "IDN", "date": "1993-01-01T00:00:00", "gdp_per_capita": 817.395116417856}, {"economy": "IDN", "date": "1994-01-01T00:00:00", "gdp_per_capita": 899.793982949817}, {"economy": "IDN", "date": "1995-01-01T00:00:00", "gdp_per_capita": 1011.22614205568}, {"economy": "IDN", "date": "1996-01-01T00:00:00", "gdp_per_capita": 1118.92133024129}, {"economy": "IDN", "date": "1997-01-01T00:00:00", "gdp_per_capita": 1044.60674832472}, {"economy": "IDN", "date": "1998-01-01T00:00:00", "gdp_per_capita": 454.877800792123}, {"economy": "IDN", "date": "1999-01-01T00:00:00", "gdp_per_capita": 657.268934667018}, {"economy": "IDN", "date": "2000-01-01T00:00:00", "gdp_per_capita": 763.711124950924}, {"economy": "IDN", "date": "2001-01-01T00:00:00", "gdp_per_capita": 732.307093405708}, {"economy": "IDN", "date": "2002-01-01T00:00:00", "gdp_per_capita": 881.002913569131}, {"economy": "IDN", "date": "2003-01-01T00:00:00", "gdp_per_capita": 1043.2105838671}, {"economy": "IDN", "date": "2004-01-01T00:00:00", "gdp_per_capita": 1126.84004447173}, {"economy": "IDN", "date": "2005-01-01T00:00:00", "gdp_per_capita": 1238.21447629488}, {"economy": "IDN", "date": "2006-01-01T00:00:00", "gdp_per_capita": 1558.31562847164}, {"economy": "IDN", "date": "2007-01-01T00:00:00", "gdp_per_capita": 1823.21976255073}, {"economy": "IDN", "date": "2008-01-01T00:00:00", "gdp_per_capita": 2124.55483920617}, {"economy": "IDN", "date": "2009-01-01T00:00:00", "gdp_per_capita": 2218.48541852977}, {"economy": "IDN", "date": "2010-01-01T00:00:00", "gdp_per_capita": 3065.68348366636}, {"economy": "IDN", "date": "2011-01-01T00:00:00", "gdp_per_capita": 3579.46442452684}, {"economy": "IDN", "date": "2012-01-01T00:00:00", "gdp_per_capita": 3632.272540431}, {"economy": "IDN", "date": "2013-01-01T00:00:00", "gdp_per_capita": 3566.60284506078}, {"economy": "IDN", "date": "2014-01-01T00:00:00", "gdp_per_capita": 3441.06808455308}, {"economy": "IDN", "date": "2015-01-01T00:00:00", "gdp_per_capita": 3288.22269737572}, {"economy": "IDN", "date": "2016-01-01T00:00:00", "gdp_per_capita": 3521.46943456251}, {"economy": "IDN", "date": "2017-01-01T00:00:00", "gdp_per_capita": 3798.88326177649}, {"economy": "IDN", "date": "2018-01-01T00:00:00", "gdp_per_capita": 3860.95353077708}, {"economy": "IDN", "date": "2019-01-01T00:00:00", "gdp_per_capita": 4106.94856173421}, {"economy": "IDN", "date": "2020-01-01T00:00:00", "gdp_per_capita": 3853.70288778903}, {"economy": "IDN", "date": "2021-01-01T00:00:00", "gdp_per_capita": 4287.17313989405}, {"economy": "IDN", "date": "2022-01-01T00:00:00", "gdp_per_capita": 4730.74548910499}, {"economy": "IDN", "date": "2023-01-01T00:00:00", "gdp_per_capita": 4876.31432703188}]}}